txtfrompdf/__init__.py
txtfrompdf/__main__.py
txtfrompdf/_pdfminer.py
txtfrompdf/extract.py
txtfrompdf/filter.py
txtfrompdf/fix_unicode.py
txtfrompdf/utils.py
txt_from_pdf-1.3.1.dist-info/LICENSE
txt_from_pdf-1.3.1.dist-info/METADATA
txt_from_pdf-1.3.1.dist-info/WHEEL
txt_from_pdf-1.3.1.dist-info/entry_points.txt
txt_from_pdf-1.3.1.dist-info/top_level.txt
txt_from_pdf-1.3.1.dist-info/RECORD
