Metadata-Version: 2.1
Name: txt-from-pdf
Version: 1.3.1
Summary: Extract clean text from PDFs.
Home-page: https://github.com/alisafaya/txt-from-pdf
Author: Ali Safaya
Author-email: alisafaya@gmail.com
License: Apache
Keywords: pdf text extraction
Classifier: Intended Audience :: Developers
Classifier: Intended Audience :: Education
Classifier: Intended Audience :: Science/Research
Classifier: License :: OSI Approved :: Apache Software License
Classifier: Operating System :: OS Independent
Classifier: Programming Language :: Python :: 3
Classifier: Programming Language :: Python :: 3.7
Classifier: Topic :: Scientific/Engineering :: Information Analysis
Classifier: Topic :: Text Processing
Classifier: Topic :: Utilities
Requires-Python: >=3.7.0
License-File: LICENSE
Requires-Dist: unicodedata2 (~=15.1.0)
Requires-Dist: PyMuPDF (~=1.24.9)
Provides-Extra: dev
Requires-Dist: black (~=23.0) ; extra == 'dev'
Requires-Dist: ruff (>=0.2) ; extra == 'dev'
